loadup/__init__.py
loadup/builder.py
loadup/cli.py
loadup-0.1.1.dist-info/licenses/LICENSE
loadup-0.1.1.dist-info/METADATA
loadup-0.1.1.dist-info/WHEEL
loadup-0.1.1.dist-info/entry_points.txt
loadup-0.1.1.dist-info/top_level.txt
loadup-0.1.1.dist-info/RECORD
