Metadata-Version: 2.4
Name: loadup
Version: 0.1.1
Summary: A smart bundler for WinUp applications, built on top of PyInstaller.
Author-email: ebaadwaheed <ebaadalt@gmail.com>
License: MIT
License-File: LICENSE
Requires-Dist: pyinstaller
Requires-Dist: click
Dynamic: license-file
